fillwise/__init__.py
fillwise/_styles.py
fillwise/_utils.py
fillwise/core.py
fillwise-1.0.1.dist-info/licenses/LICENSE
fillwise-1.0.1.dist-info/METADATA
fillwise-1.0.1.dist-info/WHEEL
fillwise-1.0.1.dist-info/top_level.txt
fillwise-1.0.1.dist-info/RECORD
