Metadata-Version: 2.4
Name: fillwise
Version: 1.0.1
Summary: Visualize group data by filling images with color proportions.
Author: Juncel
License: MIT License
Project-URL: Homepage, https://github.com/j-ncel/Fillwise
Project-URL: Repository, https://github.com/j-ncel/Fillwise
Keywords: image manipulation,data visualization,group comparison,visual encoding,charting library,visual storytelling,custom chart,mask fill,data art,python
Classifier: Programming Language :: Python :: 3
Classifier: Operating System :: OS Independent
Classifier: License :: OSI Approved :: MIT License
License-File: LICENSE
Requires-Dist: numpy
Requires-Dist: pandas
Requires-Dist: Pillow
Dynamic: license-file
